gpt4_openai/__init__.py
gpt4_openai/driver.py
gpt4_openai_api-0.8.1.dist-info/METADATA
gpt4_openai_api-0.8.1.dist-info/WHEEL
gpt4_openai_api-0.8.1.dist-info/top_level.txt
gpt4_openai_api-0.8.1.dist-info/RECORD
