Metadata-Version: 2.1
Name: gpt4-openai-api
Version: 0.8.1
Summary: Python package for unofficial GPT-4 API access via chat.openai.com using Chrome browser via Selenium
Home-page: https://github.com/Erol444/gpt4-openai-api
Author: Erol444
Author-email: erol123444@gmail.com
Classifier: Development Status :: 3 - Alpha
Classifier: Intended Audience :: Developers
Classifier: License :: OSI Approved :: MIT License
Classifier: Programming Language :: Python :: 3
Classifier: Programming Language :: Python :: 3.6
Classifier: Programming Language :: Python :: 3.7
Classifier: Programming Language :: Python :: 3.8
Classifier: Programming Language :: Python :: 3.9
Classifier: Programming Language :: Python :: 3.10
Requires-Python: >=3.6
Requires-Dist: undetected-chromedriver >=3.5.3
Requires-Dist: markdownify >=0.11.6
Requires-Dist: langchain
